{
  "initial_balance": 10000,
  "final_balance": 15351.23,
  "total_return": 53.51,
  "total_pnl": 2614.09,
  "total_trades": 76,
  "win_count": 60,
  "loss_count": 16,
  "win_rate": 0.7894736842105263,
  "avg_pnl": 34.4,
  "avg_win": 76.31,
  "avg_loss": -122.8,
  "best_trade": 194.34,
  "worst_trade": -151.47,
  "gross_profit": 4578.81,
  "gross_loss": 1964.72,
  "profit_factor": 2.33,
  "expectancy": 34.4,
  "rr_realized": 0.62,
  "max_drawdown": 293.84,
  "max_drawdown_pct": 2.13,
  "max_consec_win": 10,
  "max_consec_loss": 2,
  "sharpe_ratio": 12.19,
  "sortino_ratio": 71.66,
  "calmar_ratio": 25.17,
  "avg_duration_bars": 8.6,
  "exit_reasons": {
    "SL": 64,
    "TP": 12
  },
  "buy_pnl": 1354.25,
  "sell_pnl": 1259.84,
  "buy_win_rate": 0.8519,
  "sell_win_rate": 0.7551,
  "blocked_trades": {
    "low_confidence": 52,
    "max_per_symbol": 63,
    "htf_filter": 91,
    "low_adx": 71,
    "pullback_filter": 47,
    "cooldown": 1
  },
  "monthly": [
    {
      "month": "2025-10",
      "pnl": 193.95999999999998,
      "trades": 8,
      "wins": 6,
      "win_rate": 0.75
    },
    {
      "month": "2025-11",
      "pnl": 190.64,
      "trades": 12,
      "wins": 8,
      "win_rate": 0.6666666666666666
    },
    {
      "month": "2025-12",
      "pnl": 488.71000000000004,
      "trades": 8,
      "wins": 7,
      "win_rate": 0.875
    },
    {
      "month": "2026-01",
      "pnl": 642.92,
      "trades": 13,
      "wins": 11,
      "win_rate": 0.8461538461538461
    },
    {
      "month": "2026-02",
      "pnl": 717.01,
      "trades": 20,
      "wins": 16,
      "win_rate": 0.8
    },
    {
      "month": "2026-03",
      "pnl": 164.21,
      "trades": 13,
      "wins": 10,
      "win_rate": 0.7692307692307693
    },
    {
      "month": "2026-04",
      "pnl": 216.64,
      "trades": 2,
      "wins": 2,
      "win_rate": 1.0
    }
  ]
}