{
  "initial_balance": 10000,
  "final_balance": 13237.79,
  "total_return": 32.38,
  "total_pnl": 1761.14,
  "total_trades": 54,
  "win_count": 44,
  "loss_count": 10,
  "win_rate": 0.8148148148148148,
  "avg_pnl": 32.61,
  "avg_win": 64.14,
  "avg_loss": -106.08,
  "best_trade": 159.19,
  "worst_trade": -130.89,
  "gross_profit": 2821.94,
  "gross_loss": 1060.8,
  "profit_factor": 2.66,
  "expectancy": 32.61,
  "rr_realized": 0.6,
  "max_drawdown": 255.29,
  "max_drawdown_pct": 2.53,
  "max_consec_win": 18,
  "max_consec_loss": 2,
  "sharpe_ratio": 12.49,
  "sortino_ratio": 89.37,
  "calmar_ratio": 12.78,
  "avg_duration_bars": 7.6,
  "exit_reasons": {
    "SL": 42,
    "TP": 12
  },
  "buy_pnl": 629.42,
  "sell_pnl": 1131.72,
  "buy_win_rate": 0.8333,
  "sell_win_rate": 0.8056,
  "blocked_trades": {
    "low_confidence": 147,
    "max_per_symbol": 32,
    "htf_filter": 63,
    "low_adx": 88,
    "pullback_filter": 23,
    "cooldown": 1
  },
  "monthly": [
    {
      "month": "2025-10",
      "pnl": -83.60999999999999,
      "trades": 5,
      "wins": 3,
      "win_rate": 0.6
    },
    {
      "month": "2025-11",
      "pnl": -161.58,
      "trades": 10,
      "wins": 6,
      "win_rate": 0.6
    },
    {
      "month": "2025-12",
      "pnl": 320.27,
      "trades": 4,
      "wins": 4,
      "win_rate": 1.0
    },
    {
      "month": "2026-01",
      "pnl": 458.82,
      "trades": 11,
      "wins": 9,
      "win_rate": 0.8181818181818182
    },
    {
      "month": "2026-02",
      "pnl": 696.03,
      "trades": 12,
      "wins": 11,
      "win_rate": 0.9166666666666666
    },
    {
      "month": "2026-03",
      "pnl": 422.72,
      "trades": 10,
      "wins": 9,
      "win_rate": 0.9
    },
    {
      "month": "2026-04",
      "pnl": 108.49000000000001,
      "trades": 2,
      "wins": 2,
      "win_rate": 1.0
    }
  ]
}